traffic_taffy/__init__.py
traffic_taffy/compare.py
traffic_taffy/comparison.py
traffic_taffy/config.py
traffic_taffy/dissection.py
traffic_taffy/dissectmany.py
traffic_taffy/dissector.py
traffic_taffy/graph.py
traffic_taffy/graphdata.py
traffic_taffy/taffy_config.py
traffic_taffy/algorithms/__init__.py
traffic_taffy/algorithms/comparecorrelation.py
traffic_taffy/algorithms/comparecorrelationchanges.py
traffic_taffy/algorithms/compareseries.py
traffic_taffy/algorithms/compareslices.py
traffic_taffy/algorithms/statistical.py
traffic_taffy/dissector_engine/__init__.py
traffic_taffy/dissector_engine/dnstap.py
traffic_taffy/dissector_engine/dpkt.py
traffic_taffy/dissector_engine/scapy.py
traffic_taffy/hooks/__init__.py
traffic_taffy/hooks/blag.py
traffic_taffy/hooks/ip2asn.py
traffic_taffy/hooks/labels.py
traffic_taffy/hooks/psl.py
traffic_taffy/iana/tables.msgpak
traffic_taffy/output/__init__.py
traffic_taffy/output/console.py
traffic_taffy/output/fsdb.py
traffic_taffy/output/memory.py
traffic_taffy/reports/__init__.py
traffic_taffy/reports/compareslicesreport.py
traffic_taffy/reports/correlationchangereport.py
traffic_taffy/reports/correlationreport.py
traffic_taffy/tests/test_compare_results.py
traffic_taffy/tests/test_config.py
traffic_taffy/tests/test_dict_merge.py
traffic_taffy/tests/test_global_config.py
traffic_taffy/tests/test_hooks.py
traffic_taffy/tests/test_normalize.py
traffic_taffy/tests/test_pcap_dissector.py
traffic_taffy/tests/test_pcap_splitter.py
traffic_taffy/tests/test_splitter.py
traffic_taffy/tests/test_value_printing.py
traffic_taffy/tools/__init__.py
traffic_taffy/tools/cache_info.py
traffic_taffy/tools/compare.py
traffic_taffy/tools/config.py
traffic_taffy/tools/dissect.py
traffic_taffy/tools/explore.py
traffic_taffy/tools/export.py
traffic_taffy/tools/graph.py
traffic_taffy-0.9.9.dist-info/METADATA
traffic_taffy-0.9.9.dist-info/WHEEL
traffic_taffy-0.9.9.dist-info/entry_points.txt
traffic_taffy-0.9.9.dist-info/licenses/LICENSE.txt
traffic_taffy-0.9.9.dist-info/RECORD
