Metadata-Version: 2.4
Name: traffic-taffy
Version: 0.9.9
Summary: A tool for doing differential analysis of pcap files
Project-URL: Homepage, https://traffic-taffy.github.io/
Author-email: Wes Hardaker <opensource@hardakers.net>
License-File: LICENSE.txt
Classifier: License :: OSI Approved :: Apache Software License
Classifier: Operating System :: OS Independent
Classifier: Programming Language :: Python :: 3
Requires-Python: >=3.7
Requires-Dist: argparse-with-config>=0.1.4
Requires-Dist: cryptography
Requires-Dist: dnssplitter
Requires-Dist: dotnest>=1.0
Requires-Dist: dpkt
Requires-Dist: ip2asn>=1.6.6
Requires-Dist: msgpack
Requires-Dist: pandas
Requires-Dist: pcap-parallel
Requires-Dist: pyfsdb
Requires-Dist: pyopenssl==22.1.0
Requires-Dist: pyqt6-charts
Requires-Dist: rich
Requires-Dist: rich-argparse
Requires-Dist: scapy
Requires-Dist: seaborn
